crawlstudio/__init__.py
crawlstudio/cli.py
crawlstudio/exceptions.py
crawlstudio/models.py
crawlstudio/utils.py
crawlstudio/backends/__init__.py
crawlstudio/backends/base.py
crawlstudio/backends/browser_use.py
crawlstudio/backends/crawl4ai.py
crawlstudio/backends/firecrawl.py
crawlstudio/backends/scrapy.py
crawlstudio-0.1.0.dist-info/METADATA
crawlstudio-0.1.0.dist-info/WHEEL
crawlstudio-0.1.0.dist-info/entry_points.txt
crawlstudio-0.1.0.dist-info/licenses/LICENSE
crawlstudio-0.1.0.dist-info/RECORD
