Metadata-Version: 2.4
Name: crawlstudio
Version: 0.1.0
Summary: Unified Python library for web crawling tools - supports Firecrawl, Crawl4AI, Scrapy, and Browser-Use backends
Project-URL: Homepage, https://github.com/aiapicore/CrawlStudio
Project-URL: Repository, https://github.com/aiapicore/CrawlStudio
Project-URL: Issues, https://github.com/aiapicore/CrawlStudio/issues
Project-URL: Documentation, https://github.com/aiapicore/CrawlStudio#readme
Author-email: Saeed Ashraf <saeedashrafv@gmail.com>, Abbas Mirmashhouri <mirmashhouri@gmail.com>
License-Expression: MIT
License-File: LICENSE
Keywords: browser automation,crawl4ai,crawling,firecrawl,scrapy,web scraping
Classifier: Development Status :: 3 - Alpha
Classifier: Intended Audience :: Developers
Classifier: License :: OSI Approved :: MIT License
Classifier: Operating System :: OS Independent
Classifier: Programming Language :: Python :: 3
Classifier: Programming Language :: Python :: 3.8
Classifier: Programming Language :: Python :: 3.9
Classifier: Programming Language :: Python :: 3.10
Classifier: Programming Language :: Python :: 3.11
Classifier: Programming Language :: Python :: 3.12
Classifier: Topic :: Internet :: WWW/HTTP :: Browsers
Classifier: Topic :: Software Development :: Libraries :: Python Modules
Requires-Python: >=3.11
Requires-Dist: aiohttp>=3.9
Requires-Dist: browser-use<0.8,>=0.7.7
Requires-Dist: crawl4ai>=0.4.24
Requires-Dist: diskcache>=5.6
Requires-Dist: firecrawl-py>=0.0.20
Requires-Dist: langchain-anthropic<0.4,>=0.3.19
Requires-Dist: langchain-core<0.4,>=0.3.33
Requires-Dist: langchain-openai<0.4,>=0.3.33
Requires-Dist: playwright>=1.54
Requires-Dist: pydantic-settings>=2.0
Requires-Dist: pydantic>=2.0
Requires-Dist: python-dotenv>=1.0
Requires-Dist: scrapy>=2.11
Provides-Extra: dev
Requires-Dist: black>=22.0; extra == 'dev'
Requires-Dist: flake8>=4.0; extra == 'dev'
Requires-Dist: mypy>=1.0; extra == 'dev'
Requires-Dist: pytest-asyncio>=0.21.0; extra == 'dev'
Requires-Dist: pytest>=7.0; extra == 'dev'
